abel/linbasex.py
abel/benchmark.py
abel/_version.py
abel/dasch.py
abel/__init__.py
abel/onion_bordas.py
abel/basex.py
abel/daun.py
abel/transform.py
abel/hansenlaw.py
abel/direct.py
abel/rbasex.py
abel/tools/polar.py
abel/tools/symmetry.py
abel/tools/analytical.py
abel/tools/io.py
abel/tools/center.py
abel/tools/__init__.py
abel/tools/circularize.py
abel/tools/transform_pairs.py
abel/tools/vmi.py
abel/tools/math.py
abel/tools/polynomial.py
abel/tests/test_basex.py
abel/tests/test_tools_center.py
abel/tests/conftest.py
abel/tests/test_transform.py
abel/tests/test_tools_transform_pairs.py
abel/tests/test_tools_analytical.py
abel/tests/test_benchmarks.py
abel/tests/test_direct.py
abel/tests/test_rbasex.py
abel/tests/test_tools_circularize.py
abel/tests/test_linbasex.py
abel/tests/__init__.py
abel/tests/test_hansenlaw.py
abel/tests/test_tools_vmi.py
abel/tests/test_dasch_methods.py
abel/tests/test_daun.py
abel/tests/test_onion_bordas.py
abel/tests/test_tools_distributions.py
abel/tests/test_tools_symmetry.py
abel/tests/test_tools_polynomial.py
abel/tests/test_math.py
abel/tests/data/README.txt
abel/lib/direct.cpython-312-darwin.so
abel/lib/__init__.py
pyabel-0.9.1.dist-info/RECORD
pyabel-0.9.1.dist-info/WHEEL
pyabel-0.9.1.dist-info/top_level.txt
pyabel-0.9.1.dist-info/METADATA
pyabel-0.9.1.dist-info/licenses/LICENSE.txt
